README
setup.py
asynchia/__init__.py
asynchia/const.py
asynchia/dsl.py
asynchia/ee.py
asynchia/forthcoming.py
asynchia/maps.py
asynchia/protocols.py
asynchia/qtmap.py
asynchia/util.py
asynchia.egg-info/PKG-INFO
asynchia.egg-info/SOURCES.txt
asynchia.egg-info/dependency_links.txt
asynchia.egg-info/top_level.txt
asynchia.egg-info/zip-safe
test/test_core.py
test/test_dsl.py
test/test_ee.py
test/test_forthcoming.py
test/test_util.py