Metadata-Version: 1.0
Name: asynchia
Version: 0.1.2
Summary: asynchia is a minimalistic asynchronous networking library.
Home-page: http://bitbucket.org/segfaulthunter/asynchia-mainline
Author: Florian Mayer
Author-email: flormayer@aim.com
License: LGPL
Keywords: async asynchronous network
Platform: UNKNOWN
